docker_compose_transfer/__init__.py
docker_compose_transfer/__main__.py
docker_compose_transfer-0.8.0.dist-info/METADATA
docker_compose_transfer-0.8.0.dist-info/WHEEL
docker_compose_transfer-0.8.0.dist-info/entry_points.txt
docker_compose_transfer-0.8.0.dist-info/top_level.txt
docker_compose_transfer-0.8.0.dist-info/RECORD
