Metadata-Version: 2.1
Name: docker-compose-transfer
Version: 0.8.0
Summary: Docker compose companion for images save/load
Home-page: https://github.com/pohmelie/docker-compose-transfer
Author: pohmelie
Author-email: multisosnooley@gmail.com
License: UNKNOWN
Platform: UNKNOWN
Classifier: Programming Language :: Python
Classifier: Programming Language :: Python :: 3
Requires-Python: >=3.5
Requires-Dist: docker
Requires-Dist: docker-compose (>=1.27.0)
Requires-Dist: tqdm (<5.0.0,>=4.23.4)
